LICENSE
MANIFEST.in
setup.py
setup.rst
Stallion.egg-info/PKG-INFO
Stallion.egg-info/SOURCES.txt
Stallion.egg-info/dependency_links.txt
Stallion.egg-info/entry_points.txt
Stallion.egg-info/not-zip-safe
Stallion.egg-info/requires.txt
Stallion.egg-info/top_level.txt
stallion/__init__.py
stallion/console.py
stallion/main.py
stallion/metadata.py
stallion/write_plist.py
stallion/static/about.png
stallion/static/ajax-global.gif
stallion/static/ajax-queue.js
stallion/static/bootstrap.min.css
stallion/static/bootstrap.min.js
stallion/static/box-icon.png
stallion/static/box.png
stallion/static/console-icon.png
stallion/static/contribute.png
stallion/static/down-arrow.png
stallion/static/extra.css
stallion/static/favicon.ico
stallion/static/info.png
stallion/static/jquery-1.7.1.min.js
stallion/static/jquery-ui-1.8.16.custom.min.js
stallion/static/left-arrow.png
stallion/static/loader.gif
stallion/static/mail.png
stallion/static/refresh-icon.png
stallion/static/stallion_icon.png
stallion/static/terminal-icon.png
stallion/static/world.png
stallion/static/css/redmond/jquery-ui-1.8.16.custom.css
stallion/static/css/redmond/images/ui-bg_flat_0_aaaaaa_40x100.png
stallion/static/css/redmond/images/ui-bg_flat_55_fbec88_40x100.png
stallion/static/css/redmond/images/ui-bg_glass_75_d0e5f5_1x400.png
stallion/static/css/redmond/images/ui-bg_glass_85_dfeffc_1x400.png
stallion/static/css/redmond/images/ui-bg_glass_95_fef1ec_1x400.png
stallion/static/css/redmond/images/ui-bg_gloss-wave_55_5c9ccc_500x100.png
stallion/static/css/redmond/images/ui-bg_inset-hard_100_f5f8f9_1x100.png
stallion/static/css/redmond/images/ui-bg_inset-hard_100_fcfdfd_1x100.png
stallion/static/css/redmond/images/ui-icons_217bc0_256x240.png
stallion/static/css/redmond/images/ui-icons_2e83ff_256x240.png
stallion/static/css/redmond/images/ui-icons_469bdd_256x240.png
stallion/static/css/redmond/images/ui-icons_6da8d5_256x240.png
stallion/static/css/redmond/images/ui-icons_cd0a0a_256x240.png
stallion/static/css/redmond/images/ui-icons_d8e7f3_256x240.png
stallion/static/css/redmond/images/ui-icons_f9bd01_256x240.png
stallion/templates/about.html
stallion/templates/console_scripts.html
stallion/templates/distribution.html
