Metadata-Version: 1.1
Name: Stallion
Version: 0.4
Summary: A Python Package Manager interface.
Home-page: https://github.com/perone/stallion/
Author: Christian S. Perone
Author-email: christian.perone@gmail.com
License: Apache License 2.0
Keywords: package manager,distribution tool,stallion
Platform: Any
Classifier: Development Status :: 4 - Beta
Classifier: Environment :: Web Environment
Classifier: License :: OSI Approved :: Apache Software License
Classifier: Operating System :: OS Independent
Classifier: Programming Language :: Python
Classifier: Topic :: Internet :: WWW/HTTP :: Dynamic Content
Classifier: Topic :: Software Development :: Libraries :: Python Modules
